audio_mixer_lib/__init__.py
audio_mixer_lib/audio_mixer.py
audio_mixer_lib-1.0.0.dist-info/METADATA
audio_mixer_lib-1.0.0.dist-info/WHEEL
audio_mixer_lib-1.0.0.dist-info/top_level.txt
audio_mixer_lib-1.0.0.dist-info/RECORD
