Metadata-Version: 2.1
Name: audio-mixer-lib
Version: 1.0.0
Summary: A library to mix audio files using Pydub
Author: Your Name
Author-email: your.email@example.com
Classifier: Programming Language :: Python :: 3
Classifier: License :: OSI Approved :: MIT License
Requires-Dist: pydub
